graphcommons.py
setup.py
graphcommons.egg-info/PKG-INFO
graphcommons.egg-info/SOURCES.txt
graphcommons.egg-info/dependency_links.txt
graphcommons.egg-info/requires.txt
graphcommons.egg-info/top_level.txt