Metadata-Version: 1.0
Name: graphcommons
Version: 1.0.1
Summary: Python Wrapper For Graph Commons API.
Home-page: https://github.com/graphcommons/graphcommons-python
Author: fatiherikli
Author-email: fatiherikli@gmail.com
License: MIT
Platform: UNKNOWN
